pyfobal/__init__.py
pyfobal/client.py
pyfobal/main.py
pyfobal/fobal_types/League.py
pyfobal/fobal_types/__init__.py
pyfobal-0.1.2.dist-info/METADATA
pyfobal-0.1.2.dist-info/WHEEL
pyfobal-0.1.2.dist-info/top_level.txt
pyfobal-0.1.2.dist-info/RECORD
